{
    "uuid": "cfia-3000496382",
    "vendorName": "INTERIS CONSULTING INC.",
    "referenceNumber": "3000496382",
    "contractDate": "2012-12-21",
    "description": "Other Professional Services                                                                                                                                                                                           499 - Other Professional Services not Elsewhere Specified - $24,408",
    "extraDescription": "",
    "objectCode": "0499",
    "contractPeriodStart": "",
    "contractPeriodEnd": "",
    "startYear": 2012,
    "endYear": 2012,
    "deliveryDate": "",
    "originalValue": 12204,
    "contractValue": 12204,
    "comments": "This contract includes one or more amendments.",
    "ownerAcronym": "cfia",
    "sourceYear": 2012,
    "sourceQuarter": 3,
    "sourceFiscal": "201213-Q3",
    "sourceFilename": "cfia\/b8c3a24b84f5584dd2e7f3970c50fbc5.html",
    "sourceURL": "http:\/\/www.inspection.gc.ca\/active\/scripts\/agen\/proactive\/contra\/contrarport.asp?lang=e&yr=2012-2013&q=3&contraID=11876&yid=9",
    "vendorClean": "INTERIS CONSULTING"
}