{
    "uuid": "just-4500107853",
    "vendorName": "PC FORMS INC.",
    "referenceNumber": "4500107853",
    "contractDate": "2012-02-14",
    "description": "0670 Computer Equipment-Hardware & Software",
    "extraDescription": "",
    "objectCode": "0670",
    "contractPeriodStart": "2012-02-14",
    "contractPeriodEnd": "2013-02-13",
    "startYear": 2012,
    "endYear": 2013,
    "deliveryDate": "",
    "originalValue": 0,
    "contractValue": 22600,
    "comments": "Av01",
    "ownerAcronym": "just",
    "sourceYear": 2011,
    "sourceQuarter": 4,
    "sourceFiscal": "201112-Q4",
    "sourceFilename": "just\/a2f79ddc9ddccd83d1b6f31c72d44379.html",
    "sourceURL": "http:\/\/www.justice.gc.ca\/eng\/trans\/pd-dp\/contra\/details.asp?yr=2011&q=4&c=6822",
    "vendorClean": "PC FORMS"
}