{
    "uuid": "just-4500082890",
    "vendorName": "AMS IMAGING (1998) INC.",
    "referenceNumber": "4500082890",
    "contractDate": "2008-09-17",
    "description": "0819 Non Professional Personal Service Contracts",
    "extraDescription": "",
    "objectCode": "0819",
    "contractPeriodStart": "2008-09-17",
    "contractPeriodEnd": "2008-12-31",
    "startYear": 2008,
    "endYear": 2008,
    "deliveryDate": "",
    "originalValue": 0,
    "contractValue": 81753.68,
    "comments": "",
    "ownerAcronym": "just",
    "sourceYear": 2008,
    "sourceQuarter": 2,
    "sourceFiscal": "200809-Q2",
    "sourceFilename": "just\/d9c6f14152e288cfad0c5ddbbbdf2623.html",
    "sourceURL": "http:\/\/www.justice.gc.ca\/eng\/trans\/pd-dp\/contra\/details.asp?yr=2008&q=2&c=4177",
    "vendorClean": "AMS IMAGING (1998)"
}