{
    "uuid": "rcmp-7093078",
    "vendorName": "LES TRICOTS DUVAL & RAYMOND LTEE",
    "referenceNumber": "7093078",
    "contractDate": "2005-11-08",
    "description": "1151- Uniforms",
    "extraDescription": "",
    "objectCode": "1151",
    "contractPeriodStart": "2005-11-08",
    "contractPeriodEnd": "2005-12-10",
    "startYear": 2005,
    "endYear": 2005,
    "deliveryDate": "2005-12-10",
    "originalValue": 10984.63,
    "contractValue": 10984.63,
    "comments": "",
    "ownerAcronym": "rcmp",
    "sourceYear": 2005,
    "sourceQuarter": 3,
    "sourceFiscal": "200506-Q3",
    "sourceFilename": "rcmp\/57907216f02a41519735365023b5b370.html",
    "sourceURL": "http:\/\/www.rcmp-grc.gc.ca\/en\/contra\/?r-id=6381",
    "vendorClean": "LES TRICOTS DUVAL & RAYMOND LTEE"
}