{
    "uuid": "rcmp-7148778",
    "vendorName": "CONTRACT FURNITURE SOURCE",
    "referenceNumber": "7148778",
    "contractDate": "2009-09-18",
    "description": "1231- Office furniture and furnishings, incl parts",
    "extraDescription": "",
    "objectCode": "1231",
    "contractPeriodStart": "2009-09-18",
    "contractPeriodEnd": "2009-10-21",
    "startYear": 2009,
    "endYear": 2009,
    "deliveryDate": "2009-10-21",
    "originalValue": 14844.21,
    "contractValue": 14844.21,
    "comments": "Standard PO This contract was competitively sourced.",
    "ownerAcronym": "rcmp",
    "sourceYear": 2009,
    "sourceQuarter": 2,
    "sourceFiscal": "200910-Q2",
    "sourceFilename": "rcmp\/7328c4dc9385f5c104a85b579557b19c.html",
    "sourceURL": "http:\/\/www.rcmp-grc.gc.ca\/en\/contra\/?r-id=22293",
    "vendorClean": "CONTRACT FURNITURE SOURCE"
}