{
    "uuid": "rcmp-7199709",
    "vendorName": "AON REED STENHOUSE INC",
    "referenceNumber": "7199709",
    "contractDate": "2014-10-06",
    "description": "859- Other business services not elsewhere specified",
    "extraDescription": "",
    "objectCode": "0859",
    "contractPeriodStart": "2014-10-06",
    "contractPeriodEnd": "2014-10-06",
    "startYear": 2014,
    "endYear": 2014,
    "deliveryDate": "2014-10-06",
    "originalValue": 36774.16,
    "contractValue": 36774.16,
    "comments": "Call up against SOA This contract was sole-sourced. contract for US Border Auto Fleet",
    "ownerAcronym": "rcmp",
    "sourceYear": 2014,
    "sourceQuarter": 3,
    "sourceFiscal": "201415-Q3",
    "sourceFilename": "rcmp\/b26d25b79ccd8aed4ce71faddb2d3cc7.html",
    "sourceURL": "http:\/\/www.rcmp-grc.gc.ca\/en\/contra\/?r-id=40056",
    "vendorClean": "AON REED STENHOUSE"
}