{
    "uuid": "rcmp-4500003962",
    "vendorName": "BIRCH NARROWS DENE NATIONS",
    "referenceNumber": "4500003962",
    "contractDate": "2015-04-01",
    "description": "510- Rental of residential buildings",
    "extraDescription": "",
    "objectCode": "0510",
    "contractPeriodStart": "2015-04-01",
    "contractPeriodEnd": "2017-03-31",
    "startYear": 2015,
    "endYear": 2017,
    "deliveryDate": "2017-03-31",
    "originalValue": 9600,
    "contractValue": 19200,
    "comments": "RCMP invoicing plan This contract was competitively sourced. This contract includes one or more amendments.",
    "ownerAcronym": "rcmp",
    "sourceYear": 2016,
    "sourceQuarter": 1,
    "sourceFiscal": "201617-Q1",
    "sourceFilename": "rcmp\/bc161bd23026a04a63ab8b08f4944b08.html",
    "sourceURL": "http:\/\/www.rcmp-grc.gc.ca\/en\/contra\/?r-id=52326",
    "vendorClean": "BIRCH NARROWS DENE NATIONS"
}