{
    "uuid": "rcmp-M901074974",
    "vendorName": "GENERAL DYNAMICS C4SYSTEMS",
    "referenceNumber": "M901074974",
    "contractDate": "2007-01-31",
    "description": "1222- Data (message\/text, and com",
    "extraDescription": "",
    "objectCode": "1222",
    "contractPeriodStart": "2007-01-31",
    "contractPeriodEnd": "2007-02-12",
    "startYear": 2007,
    "endYear": 2007,
    "deliveryDate": "2007-02-12",
    "originalValue": 12710.72,
    "contractValue": 12710.72,
    "comments": "",
    "ownerAcronym": "rcmp",
    "sourceYear": 2006,
    "sourceQuarter": 4,
    "sourceFiscal": "200607-Q4",
    "sourceFilename": "rcmp\/c1791a5eca555667183f6b5964d44a39.html",
    "sourceURL": "http:\/\/www.rcmp-grc.gc.ca\/en\/contra\/?r-id=11142",
    "vendorClean": "GENERAL DYNAMICS C4SYSTEMS"
}