{
    "uuid": "rcmp-7087781",
    "vendorName": "STANDARD ROOFING(G.P.)LTD",
    "referenceNumber": "7087781",
    "contractDate": "2005-06-07",
    "description": "630- Office buildings",
    "extraDescription": "",
    "objectCode": "0630",
    "contractPeriodStart": "2005-06-07",
    "contractPeriodEnd": "2005-09-30",
    "startYear": 2005,
    "endYear": 2005,
    "deliveryDate": "2005-09-30",
    "originalValue": 14277,
    "contractValue": 14277,
    "comments": "",
    "ownerAcronym": "rcmp",
    "sourceYear": 2005,
    "sourceQuarter": 1,
    "sourceFiscal": "200506-Q1",
    "sourceFilename": "rcmp\/c5e315219995690159304fcab3d48a8e.html",
    "sourceURL": "http:\/\/www.rcmp-grc.gc.ca\/en\/contra\/?r-id=5097",
    "vendorClean": "STANDARD ROOFING(GP)LTD"
}