{
    "uuid": "rcmp-7131128",
    "vendorName": "SMITH STOCKLEY LTD.",
    "referenceNumber": "7131128",
    "contractDate": "2008-06-02",
    "description": "630- Office buildings",
    "extraDescription": "",
    "objectCode": "0630",
    "contractPeriodStart": "2008-06-02",
    "contractPeriodEnd": "2008-07-31",
    "startYear": 2008,
    "endYear": 2008,
    "deliveryDate": "2008-07-31",
    "originalValue": 23165,
    "contractValue": 23165,
    "comments": "",
    "ownerAcronym": "rcmp",
    "sourceYear": 2008,
    "sourceQuarter": 1,
    "sourceFiscal": "200809-Q1",
    "sourceFilename": "rcmp\/cbec9eccac70ae76c02246f7821f2c85.html",
    "sourceURL": "http:\/\/www.rcmp-grc.gc.ca\/en\/contra\/?r-id=16818",
    "vendorClean": "SMITH STOCKLEY"
}