{
    "uuid": "pc-45222588",
    "vendorName": "Metrographics Design and",
    "referenceNumber": "45222588",
    "contractDate": "2007\/12\/05",
    "description": "351 Communications professional services not elsewhere specified",
    "extraDescription": "",
    "objectCode": "0351",
    "contractPeriodStart": "2007\/12\/05",
    "contractPeriodEnd": "2008\/03\/18",
    "startYear": 2007,
    "endYear": 2008,
    "deliveryDate": "2008\/03\/18",
    "originalValue": 28245,
    "contractValue": 28245,
    "comments": "",
    "ownerAcronym": "pc",
    "sourceYear": 2007,
    "sourceQuarter": 4,
    "sourceFiscal": "200708-Q4",
    "sourceFilename": "pc\/989cf1ba48cb51caae487288de52a52f.html",
    "sourceURL": "http:\/\/www.pc.gc.ca\/apps\/pdc\/index_E.asp?oqYEAR=2007-2008&oqQUARTER=4&oqCONTRACT_ID=27221",
    "vendorClean": "METROGRAPHICS DESIGN AND"
}