{
    "uuid": "tc-T8080-120207",
    "vendorName": "ANVIL INTEGRATED SOLUTIONS INC",
    "referenceNumber": "T8080-120207",
    "contractDate": "2013\/2\/1",
    "description": "Info Tech & Telecom Consltnts",
    "extraDescription": "",
    "objectCode": "",
    "contractPeriodStart": "2013\/2\/1",
    "contractPeriodEnd": "2013\/3\/31",
    "startYear": 2013,
    "endYear": 2013,
    "deliveryDate": "N\/A",
    "originalValue": 24973,
    "contractValue": 24973,
    "comments": "This contract was sole sourced.",
    "ownerAcronym": "tc",
    "sourceYear": 2012,
    "sourceQuarter": 4,
    "sourceFiscal": "201213-Q4",
    "sourceFilename": "tc\/2054e3a69907cfd9862158beabd8bfd3.html",
    "sourceURL": "http:\/\/wwwapps.tc.gc.ca\/Corp-Serv-Gen\/2\/PDC-DPC\/contract\/detail.aspx?Contract_ID=538622&year=2012&Quarter=4",
    "vendorClean": "ANVIL INTEGRATED SOLUTIONS"
}