{
    "uuid": "nrcan-3000587303",
    "vendorName": "PETER EDWARDS CO",
    "referenceNumber": "3000587303",
    "contractDate": "2015-08-14",
    "description": "859 Other Business Services not Elsewhere Specified",
    "extraDescription": "Market analysis Gas-Fired & Oil-Fired Water heaters",
    "objectCode": "0859",
    "contractPeriodStart": "2015-08-14",
    "contractPeriodEnd": "2015-11-27",
    "startYear": 2015,
    "endYear": 2015,
    "deliveryDate": "",
    "originalValue": 40115,
    "contractValue": 40115,
    "comments": "Call-up against a PWGSC procurement tool. This contract was competitively sourced.",
    "ownerAcronym": "nrcan",
    "sourceYear": 2015,
    "sourceQuarter": 2,
    "sourceFiscal": "201516-Q2",
    "sourceFilename": "nrcan\/57cf6845666ee1344dee66bb10e0bace.html",
    "sourceURL": "http:\/\/www2.nrcan-rncan.gc.ca\/dc-dpm\/index.cfm?fuseaction=r.d&lang=eng&fisc=2015-2016&qrt=02&id=44006",
    "vendorClean": "PETER EDWARDS CO"
}