{
    "uuid": "ic-3505840",
    "vendorName": "CANON CANADA INC.",
    "referenceNumber": "3505840",
    "contractDate": "2007-01-01",
    "description": "Rental of machinery, office furniture and fixtures and other equipment",
    "extraDescription": "",
    "objectCode": "",
    "contractPeriodStart": "2007-01-01",
    "contractPeriodEnd": "2009-12-31",
    "startYear": 2007,
    "endYear": 2009,
    "deliveryDate": "",
    "originalValue": 0,
    "contractValue": 16430,
    "comments": "",
    "ownerAcronym": "ic",
    "sourceYear": 2006,
    "sourceQuarter": 3,
    "sourceFiscal": "200607-Q3",
    "sourceFilename": "ic\/33001936a62c8072b260b1710291083c.html",
    "sourceURL": "\/app\/scr\/ic\/cr\/contract.html?id=3718",
    "vendorClean": "CANON CANADA"
}