{
    "uuid": "ic-3014917",
    "vendorName": "ONX ENTERPRISE SOLUTIONS",
    "referenceNumber": "3014917",
    "contractDate": "2005-02-18",
    "description": "Computer software",
    "extraDescription": "",
    "objectCode": "",
    "contractPeriodStart": "2005-02-18",
    "contractPeriodEnd": "2005-03-11",
    "startYear": 2005,
    "endYear": 2005,
    "deliveryDate": "",
    "originalValue": 0,
    "contractValue": 10242,
    "comments": "",
    "ownerAcronym": "ic",
    "sourceYear": 2004,
    "sourceQuarter": 4,
    "sourceFiscal": "200405-Q4",
    "sourceFilename": "ic\/aaacab166d9ed3e338005767042ef0e0.html",
    "sourceURL": "\/app\/scr\/ic\/cr\/contract.html?id=1633",
    "vendorClean": "ONX ENTERPRISE SOLUTIONS"
}