{
    "uuid": "ic-3512694",
    "vendorName": "KNOWLEDGE CIRCLE LEARNING SERVICES",
    "referenceNumber": "3512694",
    "contractDate": "2013-09-16",
    "description": "Tuition fees and costs of attending courses including seminars not elsewhere specified",
    "extraDescription": "",
    "objectCode": "",
    "contractPeriodStart": "2013-09-16",
    "contractPeriodEnd": "2014-03-14",
    "startYear": 2013,
    "endYear": 2014,
    "deliveryDate": "",
    "originalValue": 18240,
    "contractValue": 18240,
    "comments": "This contract was competitively sourced.",
    "ownerAcronym": "ic",
    "sourceYear": 2013,
    "sourceQuarter": 2,
    "sourceFiscal": "201314-Q2",
    "sourceFilename": "ic\/dcd8c28439e9c60350af215107fca8c1.html",
    "sourceURL": "\/app\/scr\/ic\/cr\/contract.html?id=94180",
    "vendorClean": "KNOWLEDGE CIRCLE LEARNING SERVICES"
}