{
    "uuid": "ic-8500228",
    "vendorName": "LOGIC 2000 INC.",
    "referenceNumber": "8500228",
    "contractDate": "2007-09-11",
    "description": "Information technology consultants",
    "extraDescription": "",
    "objectCode": "",
    "contractPeriodStart": "2007-09-11",
    "contractPeriodEnd": "2008-03-07",
    "startYear": 2007,
    "endYear": 2008,
    "deliveryDate": "",
    "originalValue": 18698,
    "contractValue": 18698,
    "comments": "",
    "ownerAcronym": "ic",
    "sourceYear": 2007,
    "sourceQuarter": 2,
    "sourceFiscal": "200708-Q2",
    "sourceFilename": "ic\/f67d39335a14176aa354f917477d432c.html",
    "sourceURL": "\/app\/scr\/ic\/cr\/contract.html?id=7349",
    "vendorClean": "LOGIC 2000"
}