{
    "uuid": "hc-1100775544",
    "vendorName": "ALEX BERLAND",
    "referenceNumber": "1100775544",
    "contractDate": "2007-09-17",
    "description": "0491 Management consulting",
    "extraDescription": "",
    "objectCode": "0491",
    "contractPeriodStart": "2007-09-17",
    "contractPeriodEnd": "2008-03-31",
    "startYear": 2007,
    "endYear": 2008,
    "deliveryDate": "-",
    "originalValue": 0,
    "contractValue": 0,
    "comments": "",
    "ownerAcronym": "hc",
    "sourceYear": 2007,
    "sourceQuarter": 2,
    "sourceFiscal": "200708-Q2",
    "sourceFilename": "hc\/1bb5d67ad0c8003a7ef3ca145e9340bb.html",
    "sourceURL": "http:\/\/www.contracts-contrats.hc-sc.gc.ca\/\/cfob\/mssid\/contractdisc.nsf\/WEBbypurpose\/6B085D1204E8FFD585257384004F1CAF?OpenDocument&lang=eng&",
    "vendorClean": "ALEX BERLAND"
}