{
    "uuid": "hc-4500259249",
    "vendorName": "VENTURE HEALTHCARE",
    "referenceNumber": "4500259249",
    "contractDate": "2011-04-10",
    "description": "0451 Other health services not elsewhere specified",
    "extraDescription": "942 - This call-up is a contract against an administrative arrangement known as a standing offer which can be initiated by PWGSC or any other department",
    "objectCode": "0451",
    "contractPeriodStart": "2011-04-10",
    "contractPeriodEnd": "2011-05-02",
    "startYear": 2011,
    "endYear": 2011,
    "deliveryDate": "",
    "originalValue": 40821.25,
    "contractValue": 40821.25,
    "comments": "Nursing Services",
    "ownerAcronym": "hc",
    "sourceYear": 2011,
    "sourceQuarter": 1,
    "sourceFiscal": "201112-Q1",
    "sourceFilename": "hc\/1f8581f2a7ecff68bc70caa174795af0.html",
    "sourceURL": "http:\/\/www.contracts-contrats.hc-sc.gc.ca\/\/cfob\/mssid\/contractdisc.nsf\/WEBbypurpose\/E6AE3049EC61C82A852578DB0058BA23?OpenDocument&lang=eng&",
    "vendorClean": "VENTURE HEALTHCARE"
}