{
    "uuid": "hc-4500192292",
    "vendorName": "ACADA?MIE DE FORMATION LINGUISTIQUE",
    "referenceNumber": "4500192292",
    "contractDate": "2008-08-25",
    "description": "0447 Tuition fees and costs of attending courses including seminars not elsewhere specified",
    "extraDescription": "",
    "objectCode": "0447",
    "contractPeriodStart": "2008-08-25",
    "contractPeriodEnd": "2008-10-24",
    "startYear": 2008,
    "endYear": 2008,
    "deliveryDate": "-",
    "originalValue": 0,
    "contractValue": 0,
    "comments": "",
    "ownerAcronym": "hc",
    "sourceYear": 2008,
    "sourceQuarter": 2,
    "sourceFiscal": "200809-Q2",
    "sourceFilename": "hc\/4b9bff982ac0de295e9cafaf34ba8d0f.html",
    "sourceURL": "http:\/\/www.contracts-contrats.hc-sc.gc.ca\/\/cfob\/mssid\/contractdisc.nsf\/WEBbypurpose\/50F290922A3B2CFA852574F30046C195?OpenDocument&lang=eng&",
    "vendorClean": "ACADA?MIE DE FORMATION LINGUISTIQUE"
}