{
    "uuid": "hc-4500146344",
    "vendorName": "ALTIS SPR",
    "referenceNumber": "4500146344",
    "contractDate": "2006-10-23",
    "description": "0813 Temporary help services",
    "extraDescription": "",
    "objectCode": "0813",
    "contractPeriodStart": "2006-10-23",
    "contractPeriodEnd": "2006-12-29",
    "startYear": 2006,
    "endYear": 2006,
    "deliveryDate": "-",
    "originalValue": 0,
    "contractValue": 0,
    "comments": "",
    "ownerAcronym": "hc",
    "sourceYear": 2006,
    "sourceQuarter": 3,
    "sourceFiscal": "200607-Q3",
    "sourceFilename": "hc\/c08e3971af3b3ed32c5ec098f69d00d5.html",
    "sourceURL": "http:\/\/www.contracts-contrats.hc-sc.gc.ca\/\/cfob\/mssid\/contractdisc.nsf\/WEBbypurpose\/6F3127812E87F34485257275005BC132?OpenDocument&lang=eng&",
    "vendorClean": "ALTIS SPR"
}