{
    "uuid": "hc-HT39944963",
    "vendorName": "COSSETTE COMMUNICATIONS INC",
    "referenceNumber": "HT39944963",
    "contractDate": "2014-11-25",
    "description": "0301 Advertising services",
    "extraDescription": "9200 - Contractual document issued by PWGSC on behalf of Health Canada",
    "objectCode": "0301",
    "contractPeriodStart": "2014-11-25",
    "contractPeriodEnd": "2014-12-31",
    "startYear": 2014,
    "endYear": 2014,
    "deliveryDate": "",
    "originalValue": 514351.14,
    "contractValue": 514351.14,
    "comments": "Advertising Services Internal Services",
    "ownerAcronym": "hc",
    "sourceYear": 2014,
    "sourceQuarter": 3,
    "sourceFiscal": "201415-Q3",
    "sourceFilename": "hc\/d429d46852f9aa5d8a08bfb22caefad7.html",
    "sourceURL": "http:\/\/www.contracts-contrats.hc-sc.gc.ca\/\/cfob\/mssid\/contractdisc.nsf\/WEBbypurpose\/CC8BF9AB978C0AB085257DFE005BB0EA?OpenDocument&lang=eng&",
    "vendorClean": "COSSETTE COMMUNICATIONS"
}