{
    "uuid": "esdc-9294-07-0221",
    "vendorName": "CANON CANADA INC",
    "referenceNumber": "9294-07-0221",
    "contractDate": "2008-02-27",
    "description": "533 Rental of Machinery, Office Furniture and Fixtures and Other Equipment",
    "extraDescription": "N\/A",
    "objectCode": "0533",
    "contractPeriodStart": "2008-03-31",
    "contractPeriodEnd": "2013-03-30",
    "startYear": 2008,
    "endYear": 2013,
    "deliveryDate": "N\/A",
    "originalValue": 24822,
    "contractValue": 24822,
    "comments": "Call-up against a standing offer",
    "ownerAcronym": "esdc",
    "sourceYear": 2007,
    "sourceQuarter": 4,
    "sourceFiscal": "200708-Q4",
    "sourceFilename": "esdc\/3cff6e09eac9be477031ab82e5fffbab.html",
    "sourceURL": "http:\/\/disclosure.esdc.gc.ca\/dp-pd\/dtlcdn-eng.jsp?section=2&id=2540&employeepositionid=null&site=1&startdate=2008-01-01&enddate=2008-03-31&quarterid=8#place268",
    "vendorClean": "CANON CANADA"
}