{
    "uuid": "cnsc-87055050784",
    "vendorName": "GAMBLE TECHNOLOGIES LTD",
    "referenceNumber": "87055050784",
    "contractDate": "February 15, 2006",
    "description": "1243 - Measuring, Controlling, Laboratory, Medical and Optical Equipment and Parts",
    "extraDescription": "",
    "objectCode": "1243",
    "contractPeriodStart": "February 15, 2006",
    "contractPeriodEnd": "March 31, 2006",
    "startYear": 2006,
    "endYear": 2006,
    "deliveryDate": "",
    "originalValue": 0,
    "contractValue": 21453.5,
    "comments": "",
    "ownerAcronym": "cnsc",
    "sourceYear": 2005,
    "sourceQuarter": 4,
    "sourceFiscal": "200506-Q4",
    "sourceFilename": "cnsc\/cc0b9ab2a023146d9e484f4bd67964a9.html",
    "sourceURL": "http:\/\/nuclearsafety.gc.ca\/eng\/transparency\/contracts-details.cfm?contract=520",
    "vendorClean": "GAMBLE TECHNOLOGIES"
}