{
    "uuid": "stats-93500-07-0010",
    "vendorName": "Loretta Fung",
    "referenceNumber": "93500-07-0010",
    "contractDate": "July 26, 2007",
    "description": "0492 Research consulting",
    "extraDescription": "",
    "objectCode": "0492",
    "contractPeriodStart": "August 7, 2007",
    "contractPeriodEnd": "March 30, 2008",
    "startYear": 2007,
    "endYear": 2008,
    "deliveryDate": "March 30, 2008",
    "originalValue": 15900,
    "contractValue": 15900,
    "comments": "Research Services - The impact of exchange Rate Movements on Services",
    "ownerAcronym": "stats",
    "sourceYear": 2007,
    "sourceQuarter": 2,
    "sourceFiscal": "200708-Q2",
    "sourceFilename": "stats\/23e286f27015b91aaa2c8a05691ac53a.html",
    "sourceURL": "\/eng\/about\/contract\/2007\/93500-07-0010",
    "vendorClean": "LORETTA FUNG"
}