{
    "uuid": "ec-K7A00-09-0008",
    "vendorName": "THE CORPORATE EXECUTIVE BOARD COMPANY",
    "referenceNumber": "K7A00-09-0008",
    "contractDate": "2010-02-03",
    "description": "1143 Printed matter, including books, newspapers, pictures, manuscripts, and forms",
    "extraDescription": "",
    "objectCode": "1143",
    "contractPeriodStart": "2010-03-16",
    "contractPeriodEnd": "2011-03-27",
    "startYear": 2010,
    "endYear": 2011,
    "deliveryDate": "",
    "originalValue": 0,
    "contractValue": 137827.73,
    "comments": "",
    "ownerAcronym": "ec",
    "sourceYear": 2009,
    "sourceQuarter": 4,
    "sourceFiscal": "200910-Q4",
    "sourceFilename": "ec\/0f0e2e0eb40be0747b777408dc9dd273.html",
    "sourceURL": "http:\/\/www.ec.gc.ca\/contracts-contrats\/index.cfm?lang=En&state=detail&id=28377&quarter=4&fiscal=2009%2C%202010",
    "vendorClean": "THE CORPORATE EXECUTIVE BOARD COMPANY"
}