{
    "uuid": "ec-K7A41-10-0022",
    "vendorName": "ORACLE CORPORATION CANADA INC.",
    "referenceNumber": "K7A41-10-0022",
    "contractDate": "2014-09-09",
    "description": "1284 Client Software",
    "extraDescription": "",
    "objectCode": "1284",
    "contractPeriodStart": "2010-08-01",
    "contractPeriodEnd": "2014-08-31",
    "startYear": 2010,
    "endYear": 2014,
    "deliveryDate": "",
    "originalValue": 0,
    "contractValue": 4992334.85,
    "comments": "Original Amount $1229159.58 This contract includes one or more amendments.",
    "ownerAcronym": "ec",
    "sourceYear": 2014,
    "sourceQuarter": 2,
    "sourceFiscal": "201415-Q2",
    "sourceFilename": "ec\/b9e5664917cb412b45b75b42345acca9.html",
    "sourceURL": "http:\/\/www.ec.gc.ca\/contracts-contrats\/index.cfm?lang=En&state=detail&id=53550&quarter=2&fiscal=2014%2C%202015",
    "vendorClean": "ORACLE CANADA"
}