{
    "uuid": "ec-KM464-11-1175",
    "vendorName": "S.J. LANDSCAPE LIMITED",
    "referenceNumber": "KM464-11-1175",
    "contractDate": "2011-10-04",
    "description": "0859 Other business services, not elsewhere specified",
    "extraDescription": "",
    "objectCode": "0859",
    "contractPeriodStart": "2011-11-01",
    "contractPeriodEnd": "2012-04-30",
    "startYear": 2011,
    "endYear": 2012,
    "deliveryDate": "",
    "originalValue": 15986.25,
    "contractValue": 15986.25,
    "comments": "",
    "ownerAcronym": "ec",
    "sourceYear": 2011,
    "sourceQuarter": 3,
    "sourceFiscal": "201112-Q3",
    "sourceFilename": "ec\/dd86f5c842fd23f7dadc56c043b81162.html",
    "sourceURL": "http:\/\/www.ec.gc.ca\/contracts-contrats\/index.cfm?lang=En&state=detail&id=40542&quarter=3&fiscal=2011%2C%202012",
    "vendorClean": "SJ LANDSCAPE LIMITED"
}