{
    "uuid": "ec-KM061-13-0078",
    "vendorName": "ANITA ENG",
    "referenceNumber": "KM061-13-0078",
    "contractDate": "2013-06-12",
    "description": "0431 Scientific consultants",
    "extraDescription": "",
    "objectCode": "0431",
    "contractPeriodStart": "2013-05-13",
    "contractPeriodEnd": "2013-08-30",
    "startYear": 2013,
    "endYear": 2013,
    "deliveryDate": "",
    "originalValue": 0,
    "contractValue": 9900,
    "comments": "Original Amount $6900.00 This contract includes one or more amendments.",
    "ownerAcronym": "ec",
    "sourceYear": 2013,
    "sourceQuarter": 1,
    "sourceFiscal": "201314-Q1",
    "sourceFilename": "ec\/f38ebc3c53037c099dfee086ea0882ac.html",
    "sourceURL": "http:\/\/www.ec.gc.ca\/contracts-contrats\/index.cfm?lang=En&state=detail&id=48328&quarter=1&fiscal=2013%2C%202014",
    "vendorClean": "ANITA ENG"
}