{
    "uuid": "lac-5Z011-10-0424\/16",
    "vendorName": "IT\/NET OTTAWA INC",
    "referenceNumber": "5Z011-10-0424\/16",
    "contractDate": "2013-11-04",
    "description": "0473 - Information Technology and Telecommunications Consultants",
    "extraDescription": "",
    "objectCode": "0473",
    "contractPeriodStart": "2013-11-04",
    "contractPeriodEnd": "2014-03-31",
    "startYear": 2013,
    "endYear": 2014,
    "deliveryDate": "",
    "originalValue": 89250,
    "contractValue": 97728.75,
    "comments": "BUSINESS PROCESS RE-ENGINEERING. This contract is a task authorization against a Public Works and Government Services Canada procurement tool.",
    "ownerAcronym": "lac",
    "sourceYear": 2013,
    "sourceQuarter": 3,
    "sourceFiscal": "201314-Q3",
    "sourceFilename": "lac\/562da64e1fea3c3d90b92f20be5d7ede.html",
    "sourceURL": "http:\/\/www.bac-lac.gc.ca\/eng\/transparency\/proactive-disclosure\/Pages\/disclosure-contracts-10k-reports-items.aspx?identifier=1005&filterquarter=3&filteryear=2013-2014",
    "vendorClean": "IT\/NET OTTAWA"
}