{
    "uuid": "cbsa-2014000863",
    "vendorName": "EMERION INC.",
    "referenceNumber": "2014000863",
    "contractDate": "2013-07-10",
    "description": "473 - Information Technology and Telecommunications Consultants",
    "extraDescription": "Public sector collection & distribution expert analyst",
    "objectCode": "0473",
    "contractPeriodStart": "2013-07-11",
    "contractPeriodEnd": "2016-07-25",
    "startYear": 2013,
    "endYear": 2016,
    "deliveryDate": "",
    "originalValue": 0,
    "contractValue": 0,
    "comments": "This contract includes one or more amendments. \/ This contract was competitively sourced.",
    "ownerAcronym": "cbsa",
    "sourceYear": 2015,
    "sourceQuarter": 1,
    "sourceFiscal": "201516-Q1",
    "sourceFilename": "cbsa\/23ab5ff704e08c716c2e4c2f0592e4d8.html",
    "sourceURL": "\/pd-dp\/contracts-contrats\/2015-2016\/q1\/c2014000863-eng.html",
    "vendorClean": "EMERION"
}