{
    "uuid": "agr-3000573478",
    "vendorName": "VWR INTERNATIONAL CO.",
    "referenceNumber": "3000573478",
    "contractDate": "2015-03-11",
    "description": "1243 Measuring, Controlling, Laboratory, Medical and Optical Equipment and Parts",
    "extraDescription": "",
    "objectCode": "1243",
    "contractPeriodStart": "2015-03-11",
    "contractPeriodEnd": "2015-03-31",
    "startYear": 2015,
    "endYear": 2015,
    "deliveryDate": "",
    "originalValue": 14844.74,
    "contractValue": 14844.74,
    "comments": "This contract was competitively sourced.",
    "ownerAcronym": "agr",
    "sourceYear": 2014,
    "sourceQuarter": 4,
    "sourceFiscal": "201415-Q4",
    "sourceFilename": "agr\/37117b74073de8629a8d0499569badbf.html",
    "sourceURL": "\/eng\/?id=1430253569994",
    "vendorClean": "VWR INTERNATIONAL CO"
}