{
    "uuid": "agr-7200001075",
    "vendorName": "IBM CANADA LTD",
    "referenceNumber": "7200001075",
    "contractDate": "2016-03-14",
    "description": "473 Information Technology and Telecommunications Consultants",
    "extraDescription": "",
    "objectCode": "0473",
    "contractPeriodStart": "2016-03-14",
    "contractPeriodEnd": "2017-03-13",
    "startYear": 2016,
    "endYear": 2017,
    "deliveryDate": "",
    "originalValue": 82575.91,
    "contractValue": 82575.91,
    "comments": "This contract was competitively sourced. Informatics Professional Services",
    "ownerAcronym": "agr",
    "sourceYear": 2015,
    "sourceQuarter": 4,
    "sourceFiscal": "201516-Q4",
    "sourceFilename": "agr\/496759ca9a2083b295c61c34d342b2d8.html",
    "sourceURL": "\/eng\/?id=1461873701153",
    "vendorClean": "IBM CANADA"
}