{
    "uuid": "pspc-700101496",
    "vendorName": "CCSI TECHNOLOGY SOLUTIONS CORP",
    "referenceNumber": "700101496",
    "contractDate": "2009-12-17",
    "description": "1226 - Computer Equipment - Large\/Medium - Mainframe, Min",
    "extraDescription": "",
    "objectCode": "1226",
    "contractPeriodStart": "2009-12-17",
    "contractPeriodEnd": "2010-01-18",
    "startYear": 2009,
    "endYear": 2010,
    "deliveryDate": "",
    "originalValue": 12380.68,
    "contractValue": 12380.68,
    "comments": "",
    "ownerAcronym": "pspc",
    "sourceYear": 2009,
    "sourceQuarter": 3,
    "sourceFiscal": "200910-Q3",
    "sourceFilename": "pspc\/2c88c6b8f5d8cc404cf32086827b875c.html",
    "sourceURL": "http:\/\/www.tpsgc-pwgsc.gc.ca\/cgi-bin\/proactive\/cl.pl?lang=eng;SCR=D;Sort=0;PF=CL200910Q3.txt;LN=2025",
    "vendorClean": "CCSI TECHNOLOGY SOLUTIONS CORP"
}