{
    "uuid": "pspc-2405R00203",
    "vendorName": "ROGERS ENTERPRISES LIMITED",
    "referenceNumber": "2405R00203",
    "contractDate": "2005-09-30",
    "description": "0446 - Training Consultants",
    "extraDescription": "",
    "objectCode": "0446",
    "contractPeriodStart": "2005-09-30",
    "contractPeriodEnd": "2005-10-03",
    "startYear": 2005,
    "endYear": 2005,
    "deliveryDate": "",
    "originalValue": 28750,
    "contractValue": 28750,
    "comments": "Contract addition not disclosed in a previous quarter.",
    "ownerAcronym": "pspc",
    "sourceYear": 2005,
    "sourceQuarter": 3,
    "sourceFiscal": "200506-Q3",
    "sourceFilename": "pspc\/b0e44957e5f71ca3823a0e5e0dfce6b9.html",
    "sourceURL": "http:\/\/www.tpsgc-pwgsc.gc.ca\/cgi-bin\/proactive\/cl.pl?lang=eng;SCR=D;Sort=0;PF=CL200506Q3.txt;LN=1521",
    "vendorClean": "ROGERS ENTERPRISES LIMITED"
}