{
    "uuid": "pspc-700099950",
    "vendorName": "CHILLIWACK FLOORS LTD.",
    "referenceNumber": "700099950",
    "contractDate": "2009-12-07",
    "description": "0639 - Institutional Buildings",
    "extraDescription": "",
    "objectCode": "0639",
    "contractPeriodStart": "2009-12-07",
    "contractPeriodEnd": "2010-01-07",
    "startYear": 2009,
    "endYear": 2010,
    "deliveryDate": "",
    "originalValue": 22188.76,
    "contractValue": 22188.76,
    "comments": "",
    "ownerAcronym": "pspc",
    "sourceYear": 2009,
    "sourceQuarter": 3,
    "sourceFiscal": "200910-Q3",
    "sourceFilename": "pspc\/b8a6e395412836b4281fd3e2b3f1d78c.html",
    "sourceURL": "http:\/\/www.tpsgc-pwgsc.gc.ca\/cgi-bin\/proactive\/cl.pl?lang=eng;SCR=D;Sort=0;PF=CL200910Q3.txt;LN=1508",
    "vendorClean": "CHILLIWACK FLOORS"
}