{
    "uuid": "pspc-700085944",
    "vendorName": "SIMPLEX INDUSTRIES INC",
    "referenceNumber": "700085944",
    "contractDate": "2009-09-02",
    "description": "0210 - Transportation of Things not Elsewhere Specified",
    "extraDescription": "",
    "objectCode": "0210",
    "contractPeriodStart": "2009-09-02",
    "contractPeriodEnd": "2010-03-31",
    "startYear": 2009,
    "endYear": 2010,
    "deliveryDate": "",
    "originalValue": 28806.23,
    "contractValue": 28806.23,
    "comments": "",
    "ownerAcronym": "pspc",
    "sourceYear": 2009,
    "sourceQuarter": 2,
    "sourceFiscal": "200910-Q2",
    "sourceFilename": "pspc\/c30e9a88b8125bb6319c1ff456027199.html",
    "sourceURL": "http:\/\/www.tpsgc-pwgsc.gc.ca\/cgi-bin\/proactive\/cl.pl?lang=eng;SCR=D;Sort=0;PF=CL200910Q2.txt;LN=10",
    "vendorClean": "SIMPLEX INDUSTRIES"
}