{
    "uuid": "pspc-E0209-07-0219",
    "vendorName": "Chase Office Interiors Inc.",
    "referenceNumber": "E0209-07-0219",
    "contractDate": "2007-09-27",
    "description": "1231 - Office Furniture and Furnishings, Including Parts",
    "extraDescription": "",
    "objectCode": "1231",
    "contractPeriodStart": "",
    "contractPeriodEnd": "",
    "startYear": 2007,
    "endYear": 2007,
    "deliveryDate": "2007-11-20",
    "originalValue": 115690.12,
    "contractValue": 115690.12,
    "comments": "",
    "ownerAcronym": "pspc",
    "sourceYear": 2007,
    "sourceQuarter": 2,
    "sourceFiscal": "200708-Q2",
    "sourceFilename": "pspc\/c7a81ef29ac60a06066203d384f90ec1.html",
    "sourceURL": "http:\/\/www.tpsgc-pwgsc.gc.ca\/cgi-bin\/proactive\/cl.pl?lang=eng;SCR=D;Sort=0;PF=CL200708Q2.txt;LN=314",
    "vendorClean": "CHASE OFFICE INTERIORS"
}