{
    "uuid": "dnd-450101091983",
    "vendorName": "Imperial Oil Limited",
    "referenceNumber": "450101091983",
    "contractDate": "2-10-2013",
    "description": "Liquid Propellants and Fuels, Petroleum Base",
    "extraDescription": "",
    "objectCode": "",
    "contractPeriodStart": "",
    "contractPeriodEnd": "",
    "startYear": 2013,
    "endYear": 2013,
    "deliveryDate": "4-10-2013",
    "originalValue": 0,
    "contractValue": 112594.1,
    "comments": "This contract was competitively sourced.This contract is a call-up against a Public Works and Government Services procurement tool.",
    "ownerAcronym": "dnd",
    "sourceYear": 2013,
    "sourceQuarter": 3,
    "sourceFiscal": "201314-Q3",
    "sourceFilename": "dnd\/07bc88083b38624930f9233551e83c15.html",
    "sourceURL": "http:\/\/www.admfincs.forces.gc.ca\/apps\/dc\/contract-contrat-eng.asp?q=3&y=2013&id=id142998",
    "vendorClean": "IMPERIAL OIL LIMITED"
}