{
    "uuid": "dnd-W0113-08A112\/001\/BOR",
    "vendorName": "Barbara L. Foley",
    "referenceNumber": "W0113-08A112\/001\/BOR",
    "contractDate": "23-10-2008",
    "description": "Food Catering Services",
    "extraDescription": "",
    "objectCode": "",
    "contractPeriodStart": "",
    "contractPeriodEnd": "",
    "startYear": 2008,
    "endYear": 2008,
    "deliveryDate": "31-12-2008",
    "originalValue": 0,
    "contractValue": 16900,
    "comments": "This contract was sole sourced.",
    "ownerAcronym": "dnd",
    "sourceYear": 2008,
    "sourceQuarter": 3,
    "sourceFiscal": "200809-Q3",
    "sourceFilename": "dnd\/18b630ade976c6d42d695c532bd9b56b.html",
    "sourceURL": "http:\/\/www.admfincs.forces.gc.ca\/apps\/dc\/contract-contrat-eng.asp?q=3&y=2008&id=id48484",
    "vendorClean": "BARBARA L FOLEY"
}