{
    "uuid": "dnd-W6399-13EB37\/003\/HP",
    "vendorName": "Hyundai Auto Canada Corp",
    "referenceNumber": "W6399-13EB37\/003\/HP",
    "contractDate": "5-7-2012",
    "description": "Passenger Motor Vehicles",
    "extraDescription": "",
    "objectCode": "",
    "contractPeriodStart": "",
    "contractPeriodEnd": "",
    "startYear": 2012,
    "endYear": 2013,
    "deliveryDate": "5-7-2013",
    "originalValue": 0,
    "contractValue": 27085,
    "comments": "This contract was competitively sourced.This contract is a call-up against a Public Works and Government Services procurement tool.",
    "ownerAcronym": "dnd",
    "sourceYear": 2012,
    "sourceQuarter": 2,
    "sourceFiscal": "201213-Q2",
    "sourceFilename": "dnd\/1c3f0414b219b742fa404aa4e4a9bc9a.html",
    "sourceURL": "http:\/\/www.admfincs.forces.gc.ca\/apps\/dc\/contract-contrat-eng.asp?q=2&y=2012&id=id122340",
    "vendorClean": "HYUNDAI AUTO CANADA CORP"
}