{
    "uuid": "dnd-W0114-175363\/001\/KIN",
    "vendorName": "Analytical Graphics, Inc.",
    "referenceNumber": "W0114-175363\/001\/KIN",
    "contractDate": "28-11-2016",
    "description": "COMPUTER SOFTWARE, MILITARY APPLICATIONS, EMERGENCY PLANNING CIVIL - OTHER THAN MICROCOMPUTERS",
    "extraDescription": "",
    "objectCode": "",
    "contractPeriodStart": "",
    "contractPeriodEnd": "",
    "startYear": 2016,
    "endYear": 2017,
    "deliveryDate": "31-3-2017",
    "originalValue": 0,
    "contractValue": 37967,
    "comments": "This contract was sole sourced.",
    "ownerAcronym": "dnd",
    "sourceYear": 2016,
    "sourceQuarter": 3,
    "sourceFiscal": "201617-Q3",
    "sourceFilename": "dnd\/240c28815236966669551262060d5acf.html",
    "sourceURL": "http:\/\/www.admfincs.forces.gc.ca\/apps\/dc\/contract-contrat-eng.asp?q=3&y=2016&id=id192700",
    "vendorClean": "ANALYTICAL GRAPHICS"
}