{
    "uuid": "dnd-W8485-173934\/001",
    "vendorName": "SIMEX DEFENCE INC.",
    "referenceNumber": "W8485-173934\/001",
    "contractDate": "5-10-2016",
    "description": "Miscellaneous Aircraft Accessories and Components",
    "extraDescription": "",
    "objectCode": "",
    "contractPeriodStart": "",
    "contractPeriodEnd": "",
    "startYear": 2016,
    "endYear": 2017,
    "deliveryDate": "7-4-2017",
    "originalValue": 0,
    "contractValue": 18810.98,
    "comments": "This item contains one or more amendments. This contract was competitively sourced.",
    "ownerAcronym": "dnd",
    "sourceYear": 2016,
    "sourceQuarter": 3,
    "sourceFiscal": "201617-Q3",
    "sourceFilename": "dnd\/26d7fa749653596530447cd9fe7e834a.html",
    "sourceURL": "http:\/\/www.admfincs.forces.gc.ca\/apps\/dc\/contract-contrat-eng.asp?q=3&y=2016&id=id191276",
    "vendorClean": "SIMEX DEFENCE"
}