{
    "uuid": "dnd-W8484-11WA43\/001\/QF",
    "vendorName": "Ultra Electronics Maritime Systems Inc.",
    "referenceNumber": "W8484-11WA43\/001\/QF",
    "contractDate": "7-12-2012",
    "description": "Underwater Sound Equipment",
    "extraDescription": "",
    "objectCode": "",
    "contractPeriodStart": "",
    "contractPeriodEnd": "",
    "startYear": 2012,
    "endYear": 2015,
    "deliveryDate": "6-12-2015",
    "originalValue": 0,
    "contractValue": 2530000,
    "comments": "This contract was sole sourced.",
    "ownerAcronym": "dnd",
    "sourceYear": 2012,
    "sourceQuarter": 3,
    "sourceFiscal": "201213-Q3",
    "sourceFilename": "dnd\/41b8e32629f2c46487bd74556f16cfd3.html",
    "sourceURL": "http:\/\/www.admfincs.forces.gc.ca\/apps\/dc\/contract-contrat-eng.asp?q=3&y=2012&id=id129523",
    "vendorClean": "ULTRA ELECTRONICS MARITIME SYSTEMS"
}