{
    "uuid": "dnd-W8486-093633\/004\/HP",
    "vendorName": "The Gear Centre",
    "referenceNumber": "W8486-093633\/004\/HP",
    "contractDate": "23-1-2009",
    "description": "Valves, Nonpowered",
    "extraDescription": "",
    "objectCode": "",
    "contractPeriodStart": "",
    "contractPeriodEnd": "",
    "startYear": 2009,
    "endYear": 2009,
    "deliveryDate": "27-2-2009",
    "originalValue": 12936,
    "contractValue": 12936,
    "comments": "This contract was competitively sourced.",
    "ownerAcronym": "dnd",
    "sourceYear": 2008,
    "sourceQuarter": 4,
    "sourceFiscal": "200809-Q4",
    "sourceFilename": "dnd\/628f95158da97432ab84fe65e633e9f6.html",
    "sourceURL": "http:\/\/www.admfincs.forces.gc.ca\/apps\/dc\/contract-contrat-eng.asp?q=4&y=2008&id=id53048",
    "vendorClean": "THE GEAR CENTRE"
}