{
    "uuid": "dnd-4501305847",
    "vendorName": "Imperial Oil Limited",
    "referenceNumber": "4501305847",
    "contractDate": "25-5-2015",
    "description": "Liquid Propellants and Fuels, Petroleum Base",
    "extraDescription": "",
    "objectCode": "",
    "contractPeriodStart": "",
    "contractPeriodEnd": "",
    "startYear": 2015,
    "endYear": 2015,
    "deliveryDate": "27-5-2015",
    "originalValue": 0,
    "contractValue": 93079.91,
    "comments": "This contract was competitively sourced. This contract is a call-up against a Public Works and Government Services procurement tool.",
    "ownerAcronym": "dnd",
    "sourceYear": 2015,
    "sourceQuarter": 1,
    "sourceFiscal": "201516-Q1",
    "sourceFilename": "dnd\/64bcd2eff9b54f8ca4c31e78afd4e7fd.html",
    "sourceURL": "http:\/\/www.admfincs.forces.gc.ca\/apps\/dc\/contract-contrat-eng.asp?q=1&y=2015&id=id168595",
    "vendorClean": "IMPERIAL OIL LIMITED"
}