{
    "uuid": "dnd-W0125-15VH33\/001\/KIN",
    "vendorName": "MDA AVIATION reg'd",
    "referenceNumber": "W0125-15VH33\/001\/KIN",
    "contractDate": "14-1-2016",
    "description": "Radar Defence Systems (R&D)",
    "extraDescription": "",
    "objectCode": "",
    "contractPeriodStart": "",
    "contractPeriodEnd": "",
    "startYear": 2016,
    "endYear": 2016,
    "deliveryDate": "31-3-2016",
    "originalValue": 0,
    "contractValue": 66670,
    "comments": "This contract was sole sourced.",
    "ownerAcronym": "dnd",
    "sourceYear": 2015,
    "sourceQuarter": 4,
    "sourceFiscal": "201516-Q4",
    "sourceFilename": "dnd\/6f72a5bba0e8a2f9f1d601b5d9594248.html",
    "sourceURL": "http:\/\/www.admfincs.forces.gc.ca\/apps\/dc\/contract-contrat-eng.asp?q=4&y=2015&id=id179140",
    "vendorClean": "MDA AVIATION REGD"
}