{
    "uuid": "dnd-W6399-5500013256",
    "vendorName": "Strategic Operations (Canada)",
    "referenceNumber": "W6399-5500013256",
    "contractDate": "29-10-2015",
    "description": "Training Aids Human Skeletons, Mannequins, Anotomical\/Medical Training Aids",
    "extraDescription": "",
    "objectCode": "",
    "contractPeriodStart": "",
    "contractPeriodEnd": "",
    "startYear": 2015,
    "endYear": 2015,
    "deliveryDate": "10-12-2015",
    "originalValue": 0,
    "contractValue": 82813.02,
    "comments": "This item was not reported previously. This contract was competitively sourced. This contract is a call-up against a Public Services and Procurement Canada procurement tool.",
    "ownerAcronym": "dnd",
    "sourceYear": 2015,
    "sourceQuarter": 3,
    "sourceFiscal": "201516-Q3",
    "sourceFilename": "dnd\/7310775f5426de693133182b8d3106d2.html",
    "sourceURL": "http:\/\/www.admfincs.forces.gc.ca\/apps\/dc\/contract-contrat-eng.asp?q=3&y=2015&id=id208052",
    "vendorClean": "STRATEGIC OPERATIONS (CANADA)"
}