{
    "uuid": "dnd-W168A-10R063\/001\/EDM",
    "vendorName": "1039711 ALBERTA LTD",
    "referenceNumber": "W168A-10R063\/001\/EDM",
    "contractDate": "10-8-2010",
    "description": "Relocation Services",
    "extraDescription": "",
    "objectCode": "",
    "contractPeriodStart": "",
    "contractPeriodEnd": "",
    "startYear": 2010,
    "endYear": 2013,
    "deliveryDate": "31-7-2013",
    "originalValue": 0,
    "contractValue": 0,
    "comments": "This is a Standing Offer. This contract was competitively sourced.",
    "ownerAcronym": "dnd",
    "sourceYear": 2010,
    "sourceQuarter": 2,
    "sourceFiscal": "201011-Q2",
    "sourceFilename": "dnd\/86a169dd5dbee93afd94659fd6f628ce.html",
    "sourceURL": "http:\/\/www.admfincs.forces.gc.ca\/apps\/dc\/contract-contrat-eng.asp?q=2&y=2010&id=id78156",
    "vendorClean": "1039711 ALBERTA"
}