{
    "uuid": "dnd-8c1d9daa888cf44de35df3ba1aee9c0f",
    "vendorName": "Pratts Limited",
    "referenceNumber": "8c1d9daa888cf44de35df3ba1aee9c0f",
    "contractDate": "27-7-2015",
    "description": "Meat, Poultry and Fish",
    "extraDescription": "",
    "objectCode": "",
    "contractPeriodStart": "",
    "contractPeriodEnd": "",
    "startYear": 2015,
    "endYear": 2015,
    "deliveryDate": "9-11-2015",
    "originalValue": 0,
    "contractValue": 0,
    "comments": "This item was not reported previously. This is a Standing Offer. This contract was competitively sourced.",
    "ownerAcronym": "dnd",
    "sourceYear": 2015,
    "sourceQuarter": 2,
    "sourceFiscal": "201516-Q2",
    "sourceFilename": "dnd\/8c1d9daa888cf44de35df3ba1aee9c0f.html",
    "sourceURL": "http:\/\/www.admfincs.forces.gc.ca\/apps\/dc\/contract-contrat-eng.asp?q=2&y=2015&id=id203837",
    "vendorClean": "PRATTS LIMITED"
}