{
    "uuid": "dnd-W3707-110038\/001\/PWY",
    "vendorName": "Island Floor Centre Ltd.",
    "referenceNumber": "W3707-110038\/001\/PWY",
    "contractDate": "9-8-2011",
    "description": "Tile Contractors, Vinyl and Linoleum",
    "extraDescription": "",
    "objectCode": "",
    "contractPeriodStart": "",
    "contractPeriodEnd": "",
    "startYear": 2011,
    "endYear": 2014,
    "deliveryDate": "31-7-2014",
    "originalValue": 0,
    "contractValue": 0,
    "comments": "This is a Standing Offer.This contract was competitively sourced.",
    "ownerAcronym": "dnd",
    "sourceYear": 2011,
    "sourceQuarter": 2,
    "sourceFiscal": "201112-Q2",
    "sourceFilename": "dnd\/a6b030c55993ba68db9172a3afd70f1e.html",
    "sourceURL": "http:\/\/www.admfincs.forces.gc.ca\/apps\/dc\/contract-contrat-eng.asp?q=2&y=2011&id=id100534",
    "vendorClean": "ISLAND FLOOR CENTRE"
}