{
    "uuid": "dnd-a9f195093850e84ff5adc8c1ee8898ce",
    "vendorName": "ROCKWELL COLLINS GOVERNMENT SYSTEMS (CANADA), INC",
    "referenceNumber": "a9f195093850e84ff5adc8c1ee8898ce",
    "contractDate": "24-10-2011",
    "description": "Radio Navigation Equipment, Airborne",
    "extraDescription": "",
    "objectCode": "",
    "contractPeriodStart": "",
    "contractPeriodEnd": "",
    "startYear": 2011,
    "endYear": 2011,
    "deliveryDate": "30-11-2011",
    "originalValue": 0,
    "contractValue": 551597,
    "comments": "This contract was sole sourced.",
    "ownerAcronym": "dnd",
    "sourceYear": 2011,
    "sourceQuarter": 3,
    "sourceFiscal": "201112-Q3",
    "sourceFilename": "dnd\/a9f195093850e84ff5adc8c1ee8898ce.html",
    "sourceURL": "http:\/\/www.admfincs.forces.gc.ca\/apps\/dc\/contract-contrat-eng.asp?q=3&y=2011&id=id107980",
    "vendorClean": "ROCKWELL COLLINS GOVERNMENT SYSTEMS (CANADA)"
}