{
    "uuid": "dnd-34053",
    "vendorName": "763471 Ontario limited",
    "referenceNumber": "34053",
    "contractDate": "28-2-2007",
    "description": "Special Trade Construction Wrk",
    "extraDescription": "",
    "objectCode": "",
    "contractPeriodStart": "",
    "contractPeriodEnd": "",
    "startYear": 2007,
    "endYear": 2007,
    "deliveryDate": "15-6-2007",
    "originalValue": 93900,
    "contractValue": 93900,
    "comments": "",
    "ownerAcronym": "dnd",
    "sourceYear": 2006,
    "sourceQuarter": 4,
    "sourceFiscal": "200607-Q4",
    "sourceFilename": "dnd\/ac45ba8c54aba85f62223e58615a33b1.html",
    "sourceURL": "http:\/\/www.admfincs.forces.gc.ca\/apps\/dc\/contract-contrat-eng.asp?q=4&y=2006&id=id22936",
    "vendorClean": "763471 ONTARIO LIMITED"
}