{
    "uuid": "dnd-W8486-116892\/001\/HN",
    "vendorName": "KVA PROTECTION INC",
    "referenceNumber": "W8486-116892\/001\/HN",
    "contractDate": "17-3-2011",
    "description": "CONVERTERS, ELECTRICAL, NONROTATING",
    "extraDescription": "",
    "objectCode": "",
    "contractPeriodStart": "",
    "contractPeriodEnd": "",
    "startYear": 2011,
    "endYear": 2011,
    "deliveryDate": "15-4-2011",
    "originalValue": 0,
    "contractValue": 274952,
    "comments": "THIS CONTRACT WAS COMPETITIVELY SOURCED.",
    "ownerAcronym": "dnd",
    "sourceYear": 2010,
    "sourceQuarter": 4,
    "sourceFiscal": "201011-Q4",
    "sourceFilename": "dnd\/b94d5924eb578d712f5d386b930f61c3.html",
    "sourceURL": "http:\/\/www.admfincs.forces.gc.ca\/apps\/dc\/contract-contrat-eng.asp?q=4&y=2010&id=id92314",
    "vendorClean": "KVA PROTECTION"
}