{
    "uuid": "dnd-30913",
    "vendorName": "XL Electric Limited",
    "referenceNumber": "30913",
    "contractDate": "15-2-2006",
    "description": "Installation work",
    "extraDescription": "",
    "objectCode": "",
    "contractPeriodStart": "",
    "contractPeriodEnd": "",
    "startYear": 2006,
    "endYear": 2006,
    "deliveryDate": "15-6-2006",
    "originalValue": 0,
    "contractValue": 109700,
    "comments": "",
    "ownerAcronym": "dnd",
    "sourceYear": 2005,
    "sourceQuarter": 4,
    "sourceFiscal": "200506-Q4",
    "sourceFilename": "dnd\/d9064e1308a38720f79cc0464511c1a7.html",
    "sourceURL": "http:\/\/www.admfincs.forces.gc.ca\/apps\/dc\/contract-contrat-eng.asp?q=4&y=2005&id=id18155",
    "vendorClean": "XL ELECTRIC LIMITED"
}