{
    "uuid": "dnd-27077",
    "vendorName": "Dobbelsteyn Service and (Fredericton)",
    "referenceNumber": "27077",
    "contractDate": "13-12-2004",
    "description": "Installation work",
    "extraDescription": "",
    "objectCode": "",
    "contractPeriodStart": "",
    "contractPeriodEnd": "",
    "startYear": 2004,
    "endYear": 2005,
    "deliveryDate": "1-6-2005",
    "originalValue": 115609,
    "contractValue": 115609,
    "comments": "",
    "ownerAcronym": "dnd",
    "sourceYear": 2004,
    "sourceQuarter": 3,
    "sourceFiscal": "200405-Q3",
    "sourceFilename": "dnd\/e2fb132fac3ee002ff584ad061907340.html",
    "sourceURL": "http:\/\/www.admfincs.forces.gc.ca\/apps\/dc\/contract-contrat-eng.asp?q=3&y=2004&id=id6061",
    "vendorClean": "DOBBELSTEYN SERVICE AND (FREDERICTON)"
}