{
    "uuid": "phac-4500262600",
    "vendorName": "DRAKE MEDOX HEALTH SERVICES",
    "referenceNumber": "4500262600",
    "contractDate": "2011-07-11",
    "description": "0451 Other health services not elsewhere specified",
    "extraDescription": "TH - This call-up is a contract against an administrative arrangement known as a standing offer which can be initiated by PWGSC or any other department",
    "objectCode": "0451",
    "contractPeriodStart": "2011-07-11",
    "contractPeriodEnd": "2011-08-05",
    "startYear": 2011,
    "endYear": 2011,
    "deliveryDate": "",
    "originalValue": 14301.74,
    "contractValue": 16608.32,
    "comments": "Nursing Services",
    "ownerAcronym": "phac",
    "sourceYear": 2011,
    "sourceQuarter": 2,
    "sourceFiscal": "201112-Q2",
    "sourceFilename": "phac\/39791cbb229e5ce38c9e57c1a3ba5cad.html",
    "sourceURL": "http:\/\/www.contracts-contrats.phac-aspc.gc.ca\/\/cfob\/mssid\/contractdisc.nsf\/WEBbypurpose\/345A1E1144DF26228525793A00615E00?OpenDocument&lang=eng&",
    "vendorClean": "DRAKE MEDOX HEALTH SERVICES"
}