{
    "uuid": "phac-4500340168",
    "vendorName": "NALY MANAGEMENT CONSULTING INC",
    "referenceNumber": "4500340168",
    "contractDate": "2015-11-03",
    "description": "0491 Management consulting",
    "extraDescription": "SAC - This is a Health Canada, Public Health Agency of Canada or PWGSC Supply Arrangement Contract",
    "objectCode": "0491",
    "contractPeriodStart": "2015-11-09",
    "contractPeriodEnd": "2016-03-31",
    "startYear": 2015,
    "endYear": 2016,
    "deliveryDate": "",
    "originalValue": 22035,
    "contractValue": 22035,
    "comments": "Program Management and Support Services Health Products",
    "ownerAcronym": "phac",
    "sourceYear": 2015,
    "sourceQuarter": 3,
    "sourceFiscal": "201516-Q3",
    "sourceFilename": "phac\/57c557db2a6217cdc4cc1e61bb251357.html",
    "sourceURL": "http:\/\/www.contracts-contrats.phac-aspc.gc.ca\/\/cfob\/mssid\/contractdisc.nsf\/WEBbypurpose\/93AEB5AF79AA6BC285257F46006C7771?OpenDocument&lang=eng&",
    "vendorClean": "NALY MANAGEMENT CONSULTING"
}