{
    "uuid": "phac-4500272831",
    "vendorName": "ODGERS BERNDTSON \/ OTTAWA INC",
    "referenceNumber": "4500272831",
    "contractDate": "2011-11-30",
    "description": "0491 Management consulting",
    "extraDescription": "942 - This call-up is a contract against an administrative arrangement known as a standing offer which can be initiated by PWGSC or any other department",
    "objectCode": "0491",
    "contractPeriodStart": "2011-11-30",
    "contractPeriodEnd": "2012-03-30",
    "startYear": 2011,
    "endYear": 2012,
    "deliveryDate": "",
    "originalValue": 89835,
    "contractValue": 89835,
    "comments": "",
    "ownerAcronym": "phac",
    "sourceYear": 2011,
    "sourceQuarter": 3,
    "sourceFiscal": "201112-Q3",
    "sourceFilename": "phac\/692dedd0727a7b4119c06fc428e441c3.html",
    "sourceURL": "http:\/\/www.contracts-contrats.phac-aspc.gc.ca\/\/cfob\/mssid\/contractdisc.nsf\/WEBbypurpose\/990E8E09B03B88C58525799200564E30?OpenDocument&lang=eng&",
    "vendorClean": "ODGERS BERNDTSON OTTAWA"
}