{
    "uuid": "sc-3039-10-0008",
    "vendorName": "ADIRONDACK TECHNOLOGIES FURNITURE INC.",
    "referenceNumber": "3039-10-0008",
    "contractDate": "2010-10-15",
    "description": "1231 Office Furniture and Furnishings, Including Parts",
    "extraDescription": "N\/A",
    "objectCode": "1231",
    "contractPeriodStart": "2010-10-15",
    "contractPeriodEnd": "2010-11-30",
    "startYear": 2010,
    "endYear": 2010,
    "deliveryDate": "2010-11-30",
    "originalValue": 20212.31,
    "contractValue": 20212.31,
    "comments": "N\/A",
    "ownerAcronym": "sc",
    "sourceYear": 2010,
    "sourceQuarter": 3,
    "sourceFiscal": "201011-Q3",
    "sourceFilename": "sc\/ba39d7025a1063626e661bc0b0fff8bc.html",
    "sourceURL": "http:\/\/disclosure.servicecanada.gc.ca\/dp-pd\/dtlcdn-eng.jsp?section=2&id=12690&employeepositionid=null&site=3&startdate=2010-10-01&enddate=2010-12-31&quarterid=18#place37",
    "vendorClean": "ADIRONDACK TECHNOLOGIES FURNITURE"
}