{
    "uuid": "pco-90006-09",
    "vendorName": "GILMORE REPRODUCTIONS",
    "referenceNumber": "90006-09",
    "contractDate": "2009-04-06",
    "description": "0321     Printing Services",
    "extraDescription": "",
    "objectCode": "0321",
    "contractPeriodStart": "2009-04-06",
    "contractPeriodEnd": "2009-05-21",
    "startYear": 2009,
    "endYear": 2009,
    "deliveryDate": "",
    "originalValue": 12751.2,
    "contractValue": 12751.2,
    "comments": "This contract is a call-up against a Public Works and Government Services Canada procurement tool.",
    "ownerAcronym": "pco",
    "sourceYear": 2009,
    "sourceQuarter": 1,
    "sourceFiscal": "200910-Q1",
    "sourceFilename": "pco\/1db19e993caac385808a0664570a48c6.html",
    "sourceURL": "http:\/\/www.pco-bcp.gc.ca\/dc\/Contracts_Contract_Details.asp?lang=eng&uniqueID=19924&quarter=20091",
    "vendorClean": "GILMORE REPRODUCTIONS"
}