{
    "uuid": "inac-20-11-6009\/3",
    "vendorName": "BRONSON CONSULTING GROUP",
    "referenceNumber": "20-11-6009\/3",
    "contractDate": "10\/21\/2013",
    "description": "0491 - MANAGEMENT CONSULTING",
    "extraDescription": "",
    "objectCode": "0491",
    "contractPeriodStart": "10\/21\/2013",
    "contractPeriodEnd": "3\/31\/2014",
    "startYear": 2013,
    "endYear": 2014,
    "deliveryDate": "",
    "originalValue": 48981.45,
    "contractValue": 48981.45,
    "comments": "Operational Program Management Support Service\/This contract was competitively sourced.\/This contract is a call-up against a departmental Standing Offer Agreement.",
    "ownerAcronym": "inac",
    "sourceYear": 2013,
    "sourceQuarter": 3,
    "sourceFiscal": "201314-Q3",
    "sourceFilename": "inac\/dea1a86129850d0647205f47451a9a27.html",
    "sourceURL": "\/prodis\/cntrcts\/13-14-q3\/ct42-eng.asp",
    "vendorClean": "BRONSON CONSULTING GROUP"
}